{"name":"练习","postlist":[{"title":"学习_单词","slug":"学习_单词","date":"2024-01-15T16:00:00.000Z","updated":"2024-01-16T13:19:02.476Z","comments":true,"path":"api/articles/学习_单词.json","excerpt":null,"keywords":null,"cover":null,"content":null,"raw":null,"categories":[],"tags":[{"name":"练习","path":"api/tags/练习.json"}]},{"title":"练习_五笔","slug":"练习_五笔","date":"2024-01-15T16:00:00.000Z","updated":"2024-02-07T14:48:23.523Z","comments":true,"path":"api/articles/练习_五笔.json","excerpt":null,"keywords":null,"cover":null,"content":null,"raw":null,"categories":[],"tags":[{"name":"练习","path":"api/tags/练习.json"}]}]}